old_icelandic_dictionary/__init__.py
old_icelandic_dictionary/dictionary.py
old_icelandic_dictionary/reader.py
old_icelandic_dictionary/resources/__init__.py
old_icelandic_dictionary/resources/default.json
old_icelandic_dictionary/resources/no-markup.json
old_icelandic_dictionary-1.0.2.dist-info/LICENSE
old_icelandic_dictionary-1.0.2.dist-info/METADATA
old_icelandic_dictionary-1.0.2.dist-info/WHEEL
old_icelandic_dictionary-1.0.2.dist-info/top_level.txt
old_icelandic_dictionary-1.0.2.dist-info/RECORD
