Metadata-Version: 2.1
Name: old-icelandic-dictionary
Version: 1.0.2
Summary: Old Icelandic dictionary for Python
Home-page: https://github.com/stscoundrel/old-icelandic-dictionary-py
Author: stscoundrel
License: UNKNOWN
Platform: UNKNOWN
Requires-Python: >=3.9
License-File: LICENSE
